[
  {
    "movie": "Dhurandhar [2D | Hindi]",
    "venue": "MovieMax: Mira Road",
    "address": "MovieMax, Prime Mall, Beverly Park, Mira-Bhayander Road, Mira Road (East), Near Shivar Garden, Mumbai, Maharashtra 401107, India",
    "chain": "MovieMax",
    "time": "01:20 AM",
    "audi": "",
    "session_id": "29943",
    "totalSeats": 363,
    "available": 338,
    "sold": 25,
    "gross": 6710.0,
    "minsLeft": 35.1,
    "city": "Mumbai",
    "state": "Maharashtra",
    "source": "BMS",
    "date": "20251225"
  },
  {
    "movie": "Dhurandhar [2D | Hindi]",
    "venue": "MovieMax: Sion",
    "address": "MovieMax, Sion Circle, Sion (East), Opposite Peninsula Restaurant, Mumbai, Maharashtra 400022, India",
    "chain": "MovieMax",
    "time": "01:25 AM",
    "audi": "Renovated",
    "session_id": "31668",
    "totalSeats": 227,
    "available": 222,
    "sold": 5,
    "gross": 1190.0,
    "minsLeft": 40.0,
    "city": "Mumbai",
    "state": "Maharashtra",
    "source": "BMS",
    "date": "20251225"
  }
]