[
  {
    "movie": "Avatar: Fire and Ash [4DX 3D | English]",
    "venue": "PVR: Global Mall, Mysore Road, Bengaluru",
    "address": "PVR Global Mall, 3rd Floor Mysore Road , Pantharapalya, Kengeri Hobli, South Taluk, Nayanda Halli, Bengaluru, Karnataka 560039, India",
    "chain": "PVR",
    "time": "06:30 AM",
    "audi": "",
    "session_id": "23701",
    "totalSeats": 92,
    "available": 40,
    "sold": 52,
    "gross": 21440.0,
    "minsLeft": 163.5,
    "city": "Bengaluru",
    "state": "Karnataka",
    "source": "BMS",
    "date": "20251222"
  }
]