{
  "Roi Roi Binale [2D | Assamese]": {
    "shows": 2,
    "gross": 42730.0,
    "sold": 177,
    "totalSeats": 830,
    "venues": 2,
    "cities": 2,
    "fastfilling": 0,
    "housefull": 0,
    "occupancy": 21.33
  },
  "Mowgli (2025) [2D | Telugu]": {
    "shows": 25,
    "gross": 48630.0,
    "sold": 370,
    "totalSeats": 5800,
    "venues": 18,
    "cities": 5,
    "fastfilling": 0,
    "housefull": 0,
    "occupancy": 6.38
  },
  "Akhanda 2: Thaandavam [2D | Telugu]": {
    "shows": 195,
    "gross": 1556956.0,
    "sold": 9625,
    "totalSeats": 69255,
    "venues": 105,
    "cities": 21,
    "fastfilling": 6,
    "housefull": 0,
    "occupancy": 13.9
  },
  "Dhurandhar [2D | Hindi]": {
    "shows": 929,
    "gross": 12825446.7,
    "sold": 44604,
    "totalSeats": 214015,
    "venues": 259,
    "cities": 63,
    "fastfilling": 109,
    "housefull": 2,
    "occupancy": 20.84
  },
  "Avatar: Fire and Ash [3D | English]": {
    "shows": 285,
    "gross": 3099667.6,
    "sold": 9608,
    "totalSeats": 64522,
    "venues": 141,
    "cities": 25,
    "fastfilling": 18,
    "housefull": 1,
    "occupancy": 14.89
  },
  "Akhanda 2: Thaandavam [3D | Telugu]": {
    "shows": 4,
    "gross": 33685.0,
    "sold": 138,
    "totalSeats": 1178,
    "venues": 4,
    "cities": 1,
    "fastfilling": 0,
    "housefull": 0,
    "occupancy": 11.71
  },
  "Avatar: Fire and Ash [2D | English]": {
    "shows": 50,
    "gross": 462056.0,
    "sold": 1413,
    "totalSeats": 10977,
    "venues": 41,
    "cities": 10,
    "fastfilling": 1,
    "housefull": 0,
    "occupancy": 12.87
  },
  "Avatar: Fire and Ash [3D | Telugu]": {
    "shows": 87,
    "gross": 719352.0,
    "sold": 3315,
    "totalSeats": 28639,
    "venues": 48,
    "cities": 9,
    "fastfilling": 0,
    "housefull": 0,
    "occupancy": 11.58
  },
  "Gurram Paapi Reddy [2D | Telugu]": {
    "shows": 28,
    "gross": 202588.0,
    "sold": 1309,
    "totalSeats": 8114,
    "venues": 20,
    "cities": 6,
    "fastfilling": 5,
    "housefull": 0,
    "occupancy": 16.13
  },
  "Bha. Bha. Ba. [2D | Malayalam]": {
    "shows": 109,
    "gross": 475625.0,
    "sold": 2736,
    "totalSeats": 32701,
    "venues": 54,
    "cities": 19,
    "fastfilling": 0,
    "housefull": 0,
    "occupancy": 8.37
  },
  "Avatar: Fire and Ash [2D | Telugu]": {
    "shows": 55,
    "gross": 489597.0,
    "sold": 3186,
    "totalSeats": 24645,
    "venues": 33,
    "cities": 9,
    "fastfilling": 2,
    "housefull": 0,
    "occupancy": 12.93
  },
  "Avatar: Fire and Ash [4DX 3D | English]": {
    "shows": 23,
    "gross": 1043110.0,
    "sold": 1689,
    "totalSeats": 2388,
    "venues": 14,
    "cities": 8,
    "fastfilling": 13,
    "housefull": 5,
    "occupancy": 70.73
  },
  "Mario (Telugu) [2D | Telugu]": {
    "shows": 7,
    "gross": 27085.0,
    "sold": 226,
    "totalSeats": 1684,
    "venues": 7,
    "cities": 2,
    "fastfilling": 0,
    "housefull": 0,
    "occupancy": 13.42
  },
  "Avatar: Fire and Ash [3D | Hindi]": {
    "shows": 185,
    "gross": 1768504.0,
    "sold": 6391,
    "totalSeats": 41062,
    "venues": 108,
    "cities": 30,
    "fastfilling": 9,
    "housefull": 0,
    "occupancy": 15.56
  },
  "Tere Ishk Mein [2D | Hindi]": {
    "shows": 18,
    "gross": 140922.0,
    "sold": 854,
    "totalSeats": 2292,
    "venues": 16,
    "cities": 8,
    "fastfilling": 4,
    "housefull": 0,
    "occupancy": 37.26
  },
  "Zootopia 2 [2D | English]": {
    "shows": 12,
    "gross": 95387.0,
    "sold": 566,
    "totalSeats": 1601,
    "venues": 9,
    "cities": 5,
    "fastfilling": 6,
    "housefull": 0,
    "occupancy": 35.35
  },
  "Demon Slayer: Kimetsu no Yaiba Infinity Castle [2D | Japanese]": {
    "shows": 1,
    "gross": 6900.0,
    "sold": 46,
    "totalSeats": 54,
    "venues": 1,
    "cities": 1,
    "fastfilling": 1,
    "housefull": 0,
    "occupancy": 85.19
  },
  "Kis Kisko Pyaar Karoon 2 [2D | Hindi]": {
    "shows": 30,
    "gross": 209030.0,
    "sold": 1268,
    "totalSeats": 4804,
    "venues": 24,
    "cities": 9,
    "fastfilling": 5,
    "housefull": 0,
    "occupancy": 26.39
  },
  "Kama and the Digital Sutras [2D | Telugu]": {
    "shows": 5,
    "gross": 8281.0,
    "sold": 61,
    "totalSeats": 691,
    "venues": 5,
    "cities": 2,
    "fastfilling": 0,
    "housefull": 0,
    "occupancy": 8.83
  },
  "Missterious [2D | Telugu]": {
    "shows": 5,
    "gross": 3780.0,
    "sold": 36,
    "totalSeats": 930,
    "venues": 4,
    "cities": 3,
    "fastfilling": 0,
    "housefull": 0,
    "occupancy": 3.87
  },
  "Oh! [2D | Telugu]": {
    "shows": 3,
    "gross": 2245.0,
    "sold": 20,
    "totalSeats": 437,
    "venues": 3,
    "cities": 1,
    "fastfilling": 0,
    "housefull": 0,
    "occupancy": 4.58
  },
  "Failure Boys [2D | Telugu]": {
    "shows": 2,
    "gross": 0.0,
    "sold": 0,
    "totalSeats": 255,
    "venues": 2,
    "cities": 2,
    "fastfilling": 0,
    "housefull": 0,
    "occupancy": 0.0
  },
  "Raju Weds Rambai [2D | Telugu]": {
    "shows": 4,
    "gross": 2100.0,
    "sold": 14,
    "totalSeats": 1628,
    "venues": 2,
    "cities": 2,
    "fastfilling": 0,
    "housefull": 0,
    "occupancy": 0.86
  },
  "Mastiii 4 [2D | Hindi]": {
    "shows": 2,
    "gross": 0.0,
    "sold": 0,
    "totalSeats": 440,
    "venues": 1,
    "cities": 1,
    "fastfilling": 0,
    "housefull": 0,
    "occupancy": 0.0
  },
  "Kalamkaval [2D | Malayalam]": {
    "shows": 41,
    "gross": 144026.24,
    "sold": 1204,
    "totalSeats": 9309,
    "venues": 27,
    "cities": 11,
    "fastfilling": 1,
    "housefull": 0,
    "occupancy": 12.93
  },
  "Kombuseevi [2D | Tamil]": {
    "shows": 15,
    "gross": 25120.0,
    "sold": 189,
    "totalSeats": 4273,
    "venues": 8,
    "cities": 6,
    "fastfilling": 0,
    "housefull": 0,
    "occupancy": 4.42
  },
  "Dheeram [2D | Malayalam]": {
    "shows": 2,
    "gross": 3636.0,
    "sold": 37,
    "totalSeats": 186,
    "venues": 2,
    "cities": 2,
    "fastfilling": 0,
    "housefull": 0,
    "occupancy": 19.89
  },
  "Summer in Bethlehem [2D | Malayalam]": {
    "shows": 2,
    "gross": 4508.0,
    "sold": 49,
    "totalSeats": 309,
    "venues": 2,
    "cities": 1,
    "fastfilling": 0,
    "housefull": 0,
    "occupancy": 15.86
  },
  "Avatar: Fire and Ash [3D | Malayalam]": {
    "shows": 2,
    "gross": 22260.0,
    "sold": 105,
    "totalSeats": 345,
    "venues": 2,
    "cities": 2,
    "fastfilling": 0,
    "housefull": 0,
    "occupancy": 30.43
  },
  "Avatar: Fire and Ash [IMAX 3D | English]": {
    "shows": 31,
    "gross": 1804384.0,
    "sold": 2976,
    "totalSeats": 9186,
    "venues": 16,
    "cities": 7,
    "fastfilling": 2,
    "housefull": 0,
    "occupancy": 32.4
  },
  "Eko [2D | Malayalam]": {
    "shows": 5,
    "gross": 35314.04,
    "sold": 334,
    "totalSeats": 828,
    "venues": 4,
    "cities": 2,
    "fastfilling": 2,
    "housefull": 0,
    "occupancy": 40.34
  },
  "Zootopia 2 [3D | English]": {
    "shows": 15,
    "gross": 209777.0,
    "sold": 687,
    "totalSeats": 1729,
    "venues": 13,
    "cities": 7,
    "fastfilling": 6,
    "housefull": 1,
    "occupancy": 39.73
  },
  "Avatar: Fire and Ash [3D | Tamil]": {
    "shows": 25,
    "gross": 122316.2,
    "sold": 655,
    "totalSeats": 9669,
    "venues": 11,
    "cities": 7,
    "fastfilling": 0,
    "housefull": 0,
    "occupancy": 6.77
  },
  "Saayavanam [2D | Tamil]": {
    "shows": 2,
    "gross": 3150.0,
    "sold": 21,
    "totalSeats": 388,
    "venues": 1,
    "cities": 1,
    "fastfilling": 0,
    "housefull": 0,
    "occupancy": 5.41
  },
  "Avatar: Fire and Ash [2D | Tamil]": {
    "shows": 3,
    "gross": 22031.4,
    "sold": 134,
    "totalSeats": 1072,
    "venues": 2,
    "cities": 1,
    "fastfilling": 0,
    "housefull": 0,
    "occupancy": 12.5
  },
  "Akhanda 2: Thaandavam [2D | Hindi]": {
    "shows": 14,
    "gross": 33820.0,
    "sold": 367,
    "totalSeats": 2026,
    "venues": 10,
    "cities": 7,
    "fastfilling": 2,
    "housefull": 0,
    "occupancy": 18.11
  },
  "Fighter Shiva [2D | Telugu]": {
    "shows": 5,
    "gross": 3942.0,
    "sold": 44,
    "totalSeats": 1148,
    "venues": 3,
    "cities": 3,
    "fastfilling": 0,
    "housefull": 0,
    "occupancy": 3.83
  },
  "Avatar: Fire and Ash [2D | Hindi]": {
    "shows": 24,
    "gross": 93675.0,
    "sold": 397,
    "totalSeats": 3660,
    "venues": 19,
    "cities": 11,
    "fastfilling": 0,
    "housefull": 0,
    "occupancy": 10.85
  },
  "Motorcycle [2D | Odia]": {
    "shows": 2,
    "gross": 0.0,
    "sold": 0,
    "totalSeats": 185,
    "venues": 1,
    "cities": 1,
    "fastfilling": 0,
    "housefull": 0,
    "occupancy": 0.0
  },
  "Sholay: The Final Cut [2D | Hindi]": {
    "shows": 3,
    "gross": 0.0,
    "sold": 0,
    "totalSeats": 284,
    "venues": 2,
    "cities": 2,
    "fastfilling": 0,
    "housefull": 0,
    "occupancy": 0.0
  },
  "Durlabh Prasad Ki Dusri Shadi [2D | Hindi]": {
    "shows": 14,
    "gross": 41584.0,
    "sold": 272,
    "totalSeats": 2498,
    "venues": 13,
    "cities": 9,
    "fastfilling": 0,
    "housefull": 1,
    "occupancy": 10.89
  },
  "The Devil [2D | Kannada]": {
    "shows": 15,
    "gross": 82000.0,
    "sold": 473,
    "totalSeats": 5135,
    "venues": 7,
    "cities": 5,
    "fastfilling": 0,
    "housefull": 0,
    "occupancy": 9.21
  },
  "Tere Ishk Mein [2D | Tamil]": {
    "shows": 2,
    "gross": 950.0,
    "sold": 5,
    "totalSeats": 294,
    "venues": 1,
    "cities": 1,
    "fastfilling": 0,
    "housefull": 0,
    "occupancy": 1.7
  },
  "Padayappa [2D | Tamil]": {
    "shows": 7,
    "gross": 16855.0,
    "sold": 144,
    "totalSeats": 2341,
    "venues": 5,
    "cities": 5,
    "fastfilling": 0,
    "housefull": 0,
    "occupancy": 6.15
  },
  "Asha (2025) [2D | Marathi]": {
    "shows": 13,
    "gross": 61256.0,
    "sold": 478,
    "totalSeats": 2035,
    "venues": 13,
    "cities": 6,
    "fastfilling": 2,
    "housefull": 0,
    "occupancy": 23.49
  },
  "Avatar: Fire and Ash [3D SCREEN X | English]": {
    "shows": 2,
    "gross": 32690.0,
    "sold": 78,
    "totalSeats": 588,
    "venues": 1,
    "cities": 1,
    "fastfilling": 0,
    "housefull": 0,
    "occupancy": 13.27
  },
  "Avatar: Fire and Ash [MX4D 3D | English]": {
    "shows": 2,
    "gross": 88900.0,
    "sold": 129,
    "totalSeats": 160,
    "venues": 1,
    "cities": 1,
    "fastfilling": 2,
    "housefull": 0,
    "occupancy": 80.62
  },
  "Gondhal [2D | Marathi]": {
    "shows": 1,
    "gross": 4650.0,
    "sold": 31,
    "totalSeats": 63,
    "venues": 1,
    "cities": 1,
    "fastfilling": 0,
    "housefull": 0,
    "occupancy": 49.21
  },
  "Uttar [2D | Marathi]": {
    "shows": 10,
    "gross": 68923.0,
    "sold": 545,
    "totalSeats": 1921,
    "venues": 9,
    "cities": 4,
    "fastfilling": 3,
    "housefull": 0,
    "occupancy": 28.37
  },
  "Tanvi: The Great [2D | Hindi]": {
    "shows": 1,
    "gross": 4480.0,
    "sold": 28,
    "totalSeats": 46,
    "venues": 1,
    "cities": 1,
    "fastfilling": 1,
    "housefull": 0,
    "occupancy": 60.87
  },
  "De De Pyaar De 2 [2D | Hindi]": {
    "shows": 1,
    "gross": 320.0,
    "sold": 2,
    "totalSeats": 46,
    "venues": 1,
    "cities": 1,
    "fastfilling": 0,
    "housefull": 0,
    "occupancy": 4.35
  },
  "Laalo - Krishna Sada Sahaayate [2D | Gujarati]": {
    "shows": 3,
    "gross": 41811.0,
    "sold": 444,
    "totalSeats": 801,
    "venues": 3,
    "cities": 2,
    "fastfilling": 2,
    "housefull": 0,
    "occupancy": 55.43
  },
  "Avatar: Fire and Ash [IMAX 3D | Hindi]": {
    "shows": 2,
    "gross": 298150.0,
    "sold": 380,
    "totalSeats": 615,
    "venues": 2,
    "cities": 2,
    "fastfilling": 2,
    "housefull": 0,
    "occupancy": 61.79
  },
  "Avatar: Fire and Ash [4DX 3D | Hindi]": {
    "shows": 9,
    "gross": 550020.0,
    "sold": 767,
    "totalSeats": 884,
    "venues": 7,
    "cities": 4,
    "fastfilling": 6,
    "housefull": 3,
    "occupancy": 86.76
  },
  "120 Bahadur [2D | Hindi]": {
    "shows": 2,
    "gross": 0.0,
    "sold": 0,
    "totalSeats": 1106,
    "venues": 1,
    "cities": 1,
    "fastfilling": 0,
    "housefull": 0,
    "occupancy": 0.0
  },
  "Maarutha [2D | Kannada]": {
    "shows": 2,
    "gross": 0.0,
    "sold": 0,
    "totalSeats": 200,
    "venues": 1,
    "cities": 1,
    "fastfilling": 0,
    "housefull": 0,
    "occupancy": 0.0
  },
  "Jeev [2D | Gujarati]": {
    "shows": 2,
    "gross": 9000.0,
    "sold": 30,
    "totalSeats": 704,
    "venues": 1,
    "cities": 1,
    "fastfilling": 0,
    "housefull": 0,
    "occupancy": 4.26
  },
  "Avatar: Fire and Ash [3D | Kannada]": {
    "shows": 2,
    "gross": 12600.0,
    "sold": 40,
    "totalSeats": 356,
    "venues": 1,
    "cities": 1,
    "fastfilling": 0,
    "housefull": 0,
    "occupancy": 11.24
  },
  "Adinaasam Vellapokkam [2D | Malayalam]": {
    "shows": 2,
    "gross": 3180.0,
    "sold": 20,
    "totalSeats": 261,
    "venues": 2,
    "cities": 2,
    "fastfilling": 0,
    "housefull": 0,
    "occupancy": 7.66
  },
  "Avatar: Fire and Ash [2D | Kannada]": {
    "shows": 2,
    "gross": 0.0,
    "sold": 0,
    "totalSeats": 1562,
    "venues": 1,
    "cities": 1,
    "fastfilling": 0,
    "housefull": 0,
    "occupancy": 0.0
  },
  "Zootopia 2 [3D | Hindi]": {
    "shows": 3,
    "gross": 9072.0,
    "sold": 48,
    "totalSeats": 303,
    "venues": 2,
    "cities": 2,
    "fastfilling": 1,
    "housefull": 0,
    "occupancy": 15.84
  },
  "Sitaaron Ke Sitaare [2D | Hindi]": {
    "shows": 1,
    "gross": 560.0,
    "sold": 5,
    "totalSeats": 152,
    "venues": 1,
    "cities": 1,
    "fastfilling": 0,
    "housefull": 0,
    "occupancy": 3.29
  },
  "Avatar: Fire and Ash [ICE 3D | Hindi]": {
    "shows": 1,
    "gross": 26120.0,
    "sold": 56,
    "totalSeats": 191,
    "venues": 1,
    "cities": 1,
    "fastfilling": 0,
    "housefull": 0,
    "occupancy": 29.32
  },
  "Wicked: For Good [3D | English]": {
    "shows": 1,
    "gross": 3401.0,
    "sold": 19,
    "totalSeats": 58,
    "venues": 1,
    "cities": 1,
    "fastfilling": 0,
    "housefull": 0,
    "occupancy": 32.76
  },
  "Avatar: Fire and Ash [ICE 3D | English]": {
    "shows": 3,
    "gross": 33140.0,
    "sold": 61,
    "totalSeats": 471,
    "venues": 2,
    "cities": 2,
    "fastfilling": 0,
    "housefull": 0,
    "occupancy": 12.95
  },
  "Avatar: Fire and Ash [MX4D 3D | Hindi]": {
    "shows": 1,
    "gross": 45600.0,
    "sold": 76,
    "totalSeats": 76,
    "venues": 1,
    "cities": 1,
    "fastfilling": 0,
    "housefull": 1,
    "occupancy": 100.0
  },
  "The Garfield Movie [2D | English]": {
    "shows": 1,
    "gross": 28800.0,
    "sold": 36,
    "totalSeats": 36,
    "venues": 1,
    "cities": 1,
    "fastfilling": 0,
    "housefull": 1,
    "occupancy": 100.0
  },
  "Prit Janmo Janmi Bhulache Nahi [2D | Gujarati]": {
    "shows": 1,
    "gross": 0.0,
    "sold": 0,
    "totalSeats": 196,
    "venues": 1,
    "cities": 1,
    "fastfilling": 0,
    "housefull": 0,
    "occupancy": 0.0
  },
  "Jinn [2D | Telugu]": {
    "shows": 3,
    "gross": 2760.0,
    "sold": 18,
    "totalSeats": 706,
    "venues": 3,
    "cities": 2,
    "fastfilling": 0,
    "housefull": 0,
    "occupancy": 2.55
  },
  "Akhanda 2: Thaandavam [2D | Tamil]": {
    "shows": 1,
    "gross": 1250.0,
    "sold": 7,
    "totalSeats": 141,
    "venues": 1,
    "cities": 1,
    "fastfilling": 0,
    "housefull": 0,
    "occupancy": 4.96
  },
  "Nuremberg [2D | English]": {
    "shows": 1,
    "gross": 3887.0,
    "sold": 13,
    "totalSeats": 30,
    "venues": 1,
    "cities": 1,
    "fastfilling": 0,
    "housefull": 0,
    "occupancy": 43.33
  },
  "Dilwale Dulhania Le Jayenge [2D | Hindi]": {
    "shows": 1,
    "gross": 5360.0,
    "sold": 124,
    "totalSeats": 1107,
    "venues": 1,
    "cities": 1,
    "fastfilling": 0,
    "housefull": 0,
    "occupancy": 11.2
  },
  "Unko Sweater: The Woolen Sweater [2D | Nepali]": {
    "shows": 1,
    "gross": 2850.0,
    "sold": 17,
    "totalSeats": 180,
    "venues": 1,
    "cities": 1,
    "fastfilling": 0,
    "housefull": 0,
    "occupancy": 9.44
  },
  "Zootopia 2 [2D | Hindi]": {
    "shows": 2,
    "gross": 12267.0,
    "sold": 63,
    "totalSeats": 288,
    "venues": 2,
    "cities": 2,
    "fastfilling": 1,
    "housefull": 0,
    "occupancy": 21.88
  },
  "Demon Slayer: Kimetsu no Yaiba Infinity Castle [2D | English]": {
    "shows": 1,
    "gross": 7912.0,
    "sold": 86,
    "totalSeats": 89,
    "venues": 1,
    "cities": 1,
    "fastfilling": 1,
    "housefull": 0,
    "occupancy": 96.63
  },
  "Now You See Me: Now You Don't [2D | English]": {
    "shows": 2,
    "gross": 4922.0,
    "sold": 31,
    "totalSeats": 137,
    "venues": 2,
    "cities": 2,
    "fastfilling": 0,
    "housefull": 0,
    "occupancy": 22.63
  },
  "SBM 1: The Past [2D | Tamil]": {
    "shows": 1,
    "gross": 0.0,
    "sold": 0,
    "totalSeats": 122,
    "venues": 1,
    "cities": 1,
    "fastfilling": 0,
    "housefull": 0,
    "occupancy": 0.0
  },
  "Five Nights at Freddy's 2 [2D | English]": {
    "shows": 1,
    "gross": 1012.0,
    "sold": 11,
    "totalSeats": 89,
    "venues": 1,
    "cities": 1,
    "fastfilling": 0,
    "housefull": 0,
    "occupancy": 12.36
  },
  "Zootopia 2 [4DX 3D | Hindi]": {
    "shows": 1,
    "gross": 5975.0,
    "sold": 25,
    "totalSeats": 92,
    "venues": 1,
    "cities": 1,
    "fastfilling": 0,
    "housefull": 0,
    "occupancy": 27.17
  },
  "Ameena [2D | Hindi]": {
    "shows": 1,
    "gross": 3000.0,
    "sold": 30,
    "totalSeats": 63,
    "venues": 1,
    "cities": 1,
    "fastfilling": 0,
    "housefull": 0,
    "occupancy": 47.62
  }
}