{
  "Champion [2D | Telugu]": {
    "shows": 195,
    "gross": 2131046.0,
    "sold": 18840,
    "totalSeats": 84672,
    "venues": 82,
    "cities": 71,
    "fastfilling": 24,
    "housefull": 0,
    "occupancy": 22.25
  },
  "Avatar: Fire and Ash [3D | Tamil]": {
    "shows": 228,
    "gross": 3730249.6,
    "sold": 26955,
    "totalSeats": 110735,
    "venues": 108,
    "cities": 72,
    "fastfilling": 25,
    "housefull": 0,
    "occupancy": 24.34
  },
  "Akhanda 2: Thaandavam [2D | Telugu]": {
    "shows": 154,
    "gross": 1565694.0,
    "sold": 13612,
    "totalSeats": 71959,
    "venues": 69,
    "cities": 62,
    "fastfilling": 18,
    "housefull": 0,
    "occupancy": 18.92
  },
  "Shambhala [2D | Telugu]": {
    "shows": 108,
    "gross": 787912.0,
    "sold": 7057,
    "totalSeats": 43059,
    "venues": 66,
    "cities": 54,
    "fastfilling": 8,
    "housefull": 0,
    "occupancy": 16.39
  },
  "Dhurandhar [2D | Hindi]": {
    "shows": 174,
    "gross": 1191017.0,
    "sold": 5892,
    "totalSeats": 34652,
    "venues": 66,
    "cities": 59,
    "fastfilling": 21,
    "housefull": 0,
    "occupancy": 17.0
  },
  "Dhandoraa [2D | Telugu]": {
    "shows": 52,
    "gross": 429811.0,
    "sold": 3789,
    "totalSeats": 23085,
    "venues": 33,
    "cities": 25,
    "fastfilling": 7,
    "housefull": 0,
    "occupancy": 16.41
  },
  "Tu Meri Main Tera Main Tera Tu Meri [2D | Hindi]": {
    "shows": 68,
    "gross": 534030.0,
    "sold": 2490,
    "totalSeats": 12176,
    "venues": 35,
    "cities": 31,
    "fastfilling": 1,
    "housefull": 5,
    "occupancy": 20.45
  },
  "Avatar: Fire and Ash [3D | Telugu]": {
    "shows": 53,
    "gross": 236598.0,
    "sold": 2734,
    "totalSeats": 19962,
    "venues": 30,
    "cities": 26,
    "fastfilling": 1,
    "housefull": 0,
    "occupancy": 13.7
  },
  "Vrusshabha [2D | Telugu]": {
    "shows": 11,
    "gross": 56734.0,
    "sold": 534,
    "totalSeats": 3329,
    "venues": 7,
    "cities": 7,
    "fastfilling": 1,
    "housefull": 0,
    "occupancy": 16.04
  },
  "Avatar: Fire and Ash [2D | Telugu]": {
    "shows": 10,
    "gross": 25823.0,
    "sold": 179,
    "totalSeats": 2689,
    "venues": 4,
    "cities": 4,
    "fastfilling": 0,
    "housefull": 0,
    "occupancy": 6.66
  },
  "Avatar: Fire and Ash [2D | Tamil]": {
    "shows": 13,
    "gross": 87450.0,
    "sold": 625,
    "totalSeats": 5168,
    "venues": 5,
    "cities": 5,
    "fastfilling": 0,
    "housefull": 0,
    "occupancy": 12.09
  },
  "Retta Thala [2D | Tamil]": {
    "shows": 149,
    "gross": 619072.9,
    "sold": 5196,
    "totalSeats": 50558,
    "venues": 86,
    "cities": 64,
    "fastfilling": 2,
    "housefull": 0,
    "occupancy": 10.28
  },
  "Sirai [2D | Tamil]": {
    "shows": 162,
    "gross": 1111613.8,
    "sold": 8496,
    "totalSeats": 54264,
    "venues": 84,
    "cities": 59,
    "fastfilling": 7,
    "housefull": 0,
    "occupancy": 15.66
  },
  "Anaconda [2D | Tamil]": {
    "shows": 64,
    "gross": 311024.7,
    "sold": 2652,
    "totalSeats": 20772,
    "venues": 45,
    "cities": 29,
    "fastfilling": 0,
    "housefull": 0,
    "occupancy": 12.77
  },
  "Kombuseevi [2D | Tamil]": {
    "shows": 25,
    "gross": 96210.0,
    "sold": 1828,
    "totalSeats": 8599,
    "venues": 18,
    "cities": 17,
    "fastfilling": 2,
    "housefull": 0,
    "occupancy": 21.26
  },
  "Eesha [2D | Telugu]": {
    "shows": 88,
    "gross": 615739.0,
    "sold": 6075,
    "totalSeats": 31455,
    "venues": 47,
    "cities": 37,
    "fastfilling": 7,
    "housefull": 0,
    "occupancy": 19.31
  },
  "Patang [2D | Telugu]": {
    "shows": 5,
    "gross": 36800.0,
    "sold": 245,
    "totalSeats": 1025,
    "venues": 4,
    "cities": 4,
    "fastfilling": 0,
    "housefull": 0,
    "occupancy": 23.9
  },
  "Avatar: Fire and Ash [3D | English]": {
    "shows": 22,
    "gross": 187353.0,
    "sold": 1021,
    "totalSeats": 4595,
    "venues": 18,
    "cities": 15,
    "fastfilling": 2,
    "housefull": 1,
    "occupancy": 22.22
  },
  "45 [2D | Kannada]": {
    "shows": 21,
    "gross": 695950.0,
    "sold": 5823,
    "totalSeats": 11194,
    "venues": 8,
    "cities": 7,
    "fastfilling": 12,
    "housefull": 0,
    "occupancy": 52.02
  },
  "Ragasiya Snehithane [2D | Tamil]": {
    "shows": 1,
    "gross": 4200.0,
    "sold": 42,
    "totalSeats": 270,
    "venues": 1,
    "cities": 1,
    "fastfilling": 0,
    "housefull": 0,
    "occupancy": 15.56
  },
  "Bad Girlz [2D | Telugu]": {
    "shows": 8,
    "gross": 11433.0,
    "sold": 64,
    "totalSeats": 1608,
    "venues": 5,
    "cities": 5,
    "fastfilling": 0,
    "housefull": 0,
    "occupancy": 3.98
  },
  "Anaconda [2D | Telugu]": {
    "shows": 18,
    "gross": 50022.0,
    "sold": 436,
    "totalSeats": 5027,
    "venues": 14,
    "cities": 12,
    "fastfilling": 0,
    "housefull": 0,
    "occupancy": 8.67
  },
  "Mark [2D | Kannada]": {
    "shows": 10,
    "gross": 312310.0,
    "sold": 2288,
    "totalSeats": 3505,
    "venues": 4,
    "cities": 4,
    "fastfilling": 4,
    "housefull": 0,
    "occupancy": 65.28
  },
  "Aghosham [2D | Malayalam]": {
    "shows": 9,
    "gross": 33725.0,
    "sold": 260,
    "totalSeats": 1911,
    "venues": 5,
    "cities": 5,
    "fastfilling": 0,
    "housefull": 0,
    "occupancy": 13.61
  },
  "Sarvam Maya [2D | Malayalam]": {
    "shows": 110,
    "gross": 2327591.62,
    "sold": 16452,
    "totalSeats": 30378,
    "venues": 36,
    "cities": 34,
    "fastfilling": 69,
    "housefull": 0,
    "occupancy": 54.16
  },
  "Vrusshabha [2D | Malayalam]": {
    "shows": 48,
    "gross": 300689.78,
    "sold": 2328,
    "totalSeats": 14786,
    "venues": 34,
    "cities": 28,
    "fastfilling": 2,
    "housefull": 0,
    "occupancy": 15.74
  },
  "Anaconda [2D | English]": {
    "shows": 9,
    "gross": 12815.6,
    "sold": 96,
    "totalSeats": 1706,
    "venues": 8,
    "cities": 8,
    "fastfilling": 0,
    "housefull": 0,
    "occupancy": 5.63
  },
  "Paruthi [2D | Tamil]": {
    "shows": 8,
    "gross": 26640.0,
    "sold": 213,
    "totalSeats": 2645,
    "venues": 5,
    "cities": 5,
    "fastfilling": 0,
    "housefull": 0,
    "occupancy": 8.05
  },
  "Bha. Bha. Ba. [2D | Malayalam]": {
    "shows": 72,
    "gross": 234659.94,
    "sold": 1722,
    "totalSeats": 16551,
    "venues": 37,
    "cities": 32,
    "fastfilling": 1,
    "housefull": 2,
    "occupancy": 10.4
  },
  "Avatar: Fire and Ash [3D | Hindi]": {
    "shows": 23,
    "gross": 251685.0,
    "sold": 1098,
    "totalSeats": 4846,
    "venues": 12,
    "cities": 12,
    "fastfilling": 4,
    "housefull": 0,
    "occupancy": 22.66
  },
  "Anaconda [2D | Hindi]": {
    "shows": 6,
    "gross": 59130.0,
    "sold": 278,
    "totalSeats": 1327,
    "venues": 4,
    "cities": 4,
    "fastfilling": 1,
    "housefull": 0,
    "occupancy": 20.95
  },
  "Avatar: Fire and Ash [2D | Hindi]": {
    "shows": 17,
    "gross": 56580.0,
    "sold": 275,
    "totalSeats": 3179,
    "venues": 9,
    "cities": 9,
    "fastfilling": 1,
    "housefull": 0,
    "occupancy": 8.65
  },
  "Projapati 2 [2D | Bengali]": {
    "shows": 3,
    "gross": 84000.0,
    "sold": 1608,
    "totalSeats": 1884,
    "venues": 1,
    "cities": 1,
    "fastfilling": 3,
    "housefull": 0,
    "occupancy": 85.35
  },
  "Dhanesh Ke Aradhna [2D | Chhattisgarhi]": {
    "shows": 6,
    "gross": 70550.0,
    "sold": 456,
    "totalSeats": 1266,
    "venues": 2,
    "cities": 2,
    "fastfilling": 0,
    "housefull": 0,
    "occupancy": 36.02
  },
  "Vande Bharat Via USA [2D | Gujarati]": {
    "shows": 3,
    "gross": 900.0,
    "sold": 3,
    "totalSeats": 400,
    "venues": 2,
    "cities": 2,
    "fastfilling": 0,
    "housefull": 0,
    "occupancy": 0.75
  },
  "Vrusshabha [2D | Hindi]": {
    "shows": 3,
    "gross": 16520.0,
    "sold": 77,
    "totalSeats": 301,
    "venues": 2,
    "cities": 2,
    "fastfilling": 0,
    "housefull": 0,
    "occupancy": 25.58
  },
  "Laalo - Krishna Sada Sahaayate [2D | Gujarati]": {
    "shows": 2,
    "gross": 7320.0,
    "sold": 35,
    "totalSeats": 212,
    "venues": 2,
    "cities": 2,
    "fastfilling": 0,
    "housefull": 0,
    "occupancy": 16.51
  },
  "Haal [2D | Malayalam]": {
    "shows": 19,
    "gross": 61324.0,
    "sold": 460,
    "totalSeats": 3716,
    "venues": 13,
    "cities": 13,
    "fastfilling": 0,
    "housefull": 1,
    "occupancy": 12.38
  },
  "Mindiyum Paranjum [2D | Malayalam]": {
    "shows": 9,
    "gross": 152388.8,
    "sold": 1167,
    "totalSeats": 3691,
    "venues": 9,
    "cities": 9,
    "fastfilling": 1,
    "housefull": 0,
    "occupancy": 31.62
  },
  "Avatar: Fire and Ash [3D | Malayalam]": {
    "shows": 5,
    "gross": 33521.8,
    "sold": 223,
    "totalSeats": 992,
    "venues": 3,
    "cities": 3,
    "fastfilling": 0,
    "housefull": 0,
    "occupancy": 22.48
  },
  "Kalamkaval [2D | Malayalam]": {
    "shows": 5,
    "gross": 4918.0,
    "sold": 42,
    "totalSeats": 957,
    "venues": 5,
    "cities": 5,
    "fastfilling": 0,
    "housefull": 0,
    "occupancy": 4.39
  },
  "Ridai Rani [2D | Santali]": {
    "shows": 2,
    "gross": 16560.0,
    "sold": 138,
    "totalSeats": 258,
    "venues": 1,
    "cities": 1,
    "fastfilling": 2,
    "housefull": 0,
    "occupancy": 53.49
  },
  "Asha [2D | Marathi]": {
    "shows": 1,
    "gross": -5000.0,
    "sold": -25,
    "totalSeats": 23,
    "venues": 1,
    "cities": 1,
    "fastfilling": 0,
    "housefull": 0,
    "occupancy": -108.7
  },
  "Ragasiya Police 115 [2D | Tamil]": {
    "shows": 1,
    "gross": 8100.0,
    "sold": 54,
    "totalSeats": 572,
    "venues": 1,
    "cities": 1,
    "fastfilling": 0,
    "housefull": 0,
    "occupancy": 9.44
  },
  "Avatar: Fire and Ash [2D | English]": {
    "shows": 1,
    "gross": 8400.0,
    "sold": 42,
    "totalSeats": 89,
    "venues": 1,
    "cities": 1,
    "fastfilling": 0,
    "housefull": 0,
    "occupancy": 47.19
  }
}